benchmark/__init__.py
benchmark/opperf/__init__.py
benchmark/opperf/opperf.py
benchmark/opperf/custom_operations/__init__.py
benchmark/opperf/custom_operations/custom_operations.py
benchmark/opperf/nd_operations/__init__.py
benchmark/opperf/nd_operations/array_rearrange.py
benchmark/opperf/nd_operations/binary_operators.py
benchmark/opperf/nd_operations/gemm_operators.py
benchmark/opperf/nd_operations/indexing_routines.py
benchmark/opperf/nd_operations/linalg_operators.py
benchmark/opperf/nd_operations/misc_operators.py
benchmark/opperf/nd_operations/nn_activation_operators.py
benchmark/opperf/nd_operations/nn_basic_operators.py
benchmark/opperf/nd_operations/nn_conv_operators.py
benchmark/opperf/nd_operations/nn_loss_operators.py
benchmark/opperf/nd_operations/nn_optimizer_operators.py
benchmark/opperf/nd_operations/random_sampling_operators.py
benchmark/opperf/nd_operations/reduction_operators.py
benchmark/opperf/nd_operations/sorting_searching_operators.py
benchmark/opperf/nd_operations/unary_operators.py
benchmark/opperf/rules/__init__.py
benchmark/opperf/rules/default_params.py
benchmark/opperf/utils/__init__.py
benchmark/opperf/utils/benchmark_utils.py
benchmark/opperf/utils/common_utils.py
benchmark/opperf/utils/ndarray_utils.py
benchmark/opperf/utils/op_registry_utils.py
benchmark/opperf/utils/profiler_utils.py
ci/__init__.py
ci/build.py
ci/build_windows.py
ci/dev_menu.py
ci/docker_cache.py
ci/docker_login.py
ci/safe_docker_run.py
ci/test_docker_cache.py
ci/test_docker_login.py
ci/test_safe_docker_run.py
ci/util.py
dmlc_tracker/__init__.py
dmlc_tracker/kubernetes.py
dmlc_tracker/launcher.py
dmlc_tracker/local.py
dmlc_tracker/mesos.py
dmlc_tracker/mpi.py
dmlc_tracker/opts.py
dmlc_tracker/sge.py
dmlc_tracker/slurm.py
dmlc_tracker/ssh.py
dmlc_tracker/submit.py
dmlc_tracker/tracker.py
dmlc_tracker/util.py
dmlc_tracker/yarn.py
mxnet/COMMIT_HASH
mxnet/__init__.py
mxnet/_api_internal.py
mxnet/_global_var.py
mxnet/_numpy_op_doc.py
mxnet/api.py
mxnet/attribute.py
mxnet_cu92-1.7.0.dist-info/LICENSE
mxnet_cu92-1.7.0.dist-info/METADATA
mxnet_cu92-1.7.0.dist-info/NOTICE
mxnet_cu92-1.7.0.dist-info/WHEEL
mxnet_cu92-1.7.0.dist-info/top_level.txt
mxnet_cu92-1.7.0.dist-info/RECORD
